{
  "users": [
    {
      "id": "testAccount",
      "username": "testAccount",
      "email": "test@test.com",
      "verified": true,
      "password": "U2FsdGVkX1+UR4X44vK1i/+JKkexYilNxUqsxsYTgxk=",
      "pokemons": [
        {
          "id": 25,
          "name": "pikachu",
          "image": "https://raw.githubusercontent.com/PokeAPI/sprites/master/sprites/pokemon/25.png",
          "hp": 35,
          "attack": 55,
          "defense": 40,
          "speed": 90,
          "favorite": true
        }
      ]
    }
  ]
}
